only_relative_import/__init__.py
only_relative_import/__main__.py
only_relative_import/main.py
only_relative_import/py.typed
only_relative_import-0.1.0.dist-info/METADATA
only_relative_import-0.1.0.dist-info/WHEEL
only_relative_import-0.1.0.dist-info/entry_points.txt
only_relative_import-0.1.0.dist-info/licenses/LICENSE
only_relative_import-0.1.0.dist-info/RECORD
